{
  "config": "{\"version\":\"5.47\",\"themeCollection\":{\"baseTheme\":{\"name\":\"CY23SU08\",\"version\":\"5.48\",\"type\":2}},\"activeSectionIndex\":6,\"defaultDrillFilterOtherVisuals\":true,\"slowDataSourceSettings\":{\"isCrossHighlightingDisabled\":false,\"isSlicerSelectionsButtonEnabled\":false,\"isFilterSelectionsButtonEnabled\":false,\"isFieldWellButtonEnabled\":false,\"isApplyAllButtonEnabled\":false},\"linguisticSchemaSyncVersion\":2,\"settings\":{\"useNewFilterPaneExperience\":true,\"allowChangeFilterTypes\":true,\"useStylableVisualContainerHeader\":true,\"queryLimitOption\":6,\"exportDataMode\":1,\"useDefaultAggregateDisplayName\":true,\"filterPaneHiddenInEditMode\":false},\"objects\":{\"section\":[{\"properties\":{\"verticalAlignment\":{\"expr\":{\"Literal\":{\"Value\":\"'Top'\"}}}}}],\"outspacePane\":[{\"properties\":{\"expanded\":{\"expr\":{\"Literal\":{\"Value\":\"true\"}}}}}]}}",
  "layoutOptimization": 0,
  "resourcePackages": [
    {
      "resourcePackage": {
        "disabled": false,
        "items": [
          {
            "name": "CY23SU08",
            "path": "BaseThemes/CY23SU08.json",
            "type": 202
          }
        ],
        "name": "SharedResources",
        "type": 2
      }
    }
  ],
  "sections": [
    {
      "config": "{}",
      "displayName": "Corr of ATK, DEF, HP, SPD",
      "displayOption": 1,
      "filters": "[]",
      "height": 720.00,
      "name": "ReportSection4b0c80287ca140dd055e",
      "visualContainers": [
        {
          "config": "{\"name\":\"5e5a9f4cde7d621080dc\",\"layouts\":[{\"id\":0,\"position\":{\"x\":0,\"y\":0,\"z\":2000,\"width\":368,\"height\":48,\"tabOrder\":2000}}],\"singleVisual\":{\"visualType\":\"textbox\",\"drillFilterOtherVisuals\":true,\"objects\":{\"general\":[{\"properties\":{\"paragraphs\":[{\"textRuns\":[{\"value\":\"Exclude Acheron, Aventurine, Gallagher\",\"textStyle\":{\"fontWeight\":\"bold\",\"fontSize\":\"14pt\"}}],\"horizontalTextAlignment\":\"center\"}]}}]}}}",
          "filters": "[]",
          "height": 48.00,
          "width": 368.00,
          "x": 0.00,
          "y": 0.00,
          "z": 2000.00
        },
        {
          "config": "{\"name\":\"c94f308f94fe02145c75\",\"layouts\":[{\"id\":0,\"position\":{\"x\":608,\"y\":256,\"z\":1000,\"width\":176,\"height\":352,\"tabOrder\":1000}}],\"singleVisual\":{\"visualType\":\"textbox\",\"drillFilterOtherVisuals\":true,\"objects\":{\"general\":[{\"properties\":{\"paragraphs\":[{\"textRuns\":[{\"value\":\"As characters leveled up, \",\"textStyle\":{\"fontSize\":\"14pt\"}},{\"value\":\"ATK\",\"textStyle\":{\"fontWeight\":\"bold\",\"fontSize\":\"14pt\"}},{\"value\":\", \",\"textStyle\":{\"fontSize\":\"14pt\"}},{\"value\":\"DEF\",\"textStyle\":{\"fontWeight\":\"bold\",\"fontSize\":\"14pt\"}},{\"value\":\", and \",\"textStyle\":{\"fontSize\":\"14pt\"}},{\"value\":\"HP \",\"textStyle\":{\"fontWeight\":\"bold\",\"fontSize\":\"14pt\"}},{\"value\":\"are increased together, while \",\"textStyle\":{\"fontSize\":\"14pt\"}},{\"value\":\"Speed \",\"textStyle\":{\"fontWeight\":\"bold\",\"fontSize\":\"14pt\"}},{\"value\":\"isn't.\",\"textStyle\":{\"fontSize\":\"14pt\"}}],\"listType\":\"bullet\"},{\"textRuns\":[{\"value\":\"\"}]}]}}]}}}",
          "filters": "[]",
          "height": 352.00,
          "width": 176.00,
          "x": 608.00,
          "y": 256.00,
          "z": 1000.00
        },
        {
          "config": "{\"name\":\"f6f770003b7adb7c4781\",\"layouts\":[{\"id\":0,\"position\":{\"x\":0,\"y\":96,\"z\":0,\"width\":608,\"height\":624,\"tabOrder\":0}}],\"singleVisual\":{\"visualType\":\"scriptVisual\",\"projections\":{\"Values\":[{\"queryRef\":\"Stats.ATK\"},{\"queryRef\":\"Stats.DEF\"},{\"queryRef\":\"Stats.HP\"},{\"queryRef\":\"Stats.Speed\"}]},\"prototypeQuery\":{\"Version\":2,\"From\":[{\"Name\":\"s\",\"Entity\":\"Stats\",\"Type\":0}],\"Select\":[{\"Column\":{\"Expression\":{\"SourceRef\":{\"Source\":\"s\"}},\"Property\":\"ATK\"},\"Name\":\"Stats.ATK\",\"NativeReferenceName\":\"ATK\"},{\"Column\":{\"Expression\":{\"SourceRef\":{\"Source\":\"s\"}},\"Property\":\"DEF\"},\"Name\":\"Stats.DEF\",\"NativeReferenceName\":\"DEF\"},{\"Column\":{\"Expression\":{\"SourceRef\":{\"Source\":\"s\"}},\"Property\":\"HP\"},\"Name\":\"Stats.HP\",\"NativeReferenceName\":\"HP\"},{\"Column\":{\"Expression\":{\"SourceRef\":{\"Source\":\"s\"}},\"Property\":\"Speed\"},\"Name\":\"Stats.Speed\",\"NativeReferenceName\":\"Speed\"}],\"OrderBy\":[{\"Direction\":1,\"Expression\":{\"Column\":{\"Expression\":{\"SourceRef\":{\"Source\":\"s\"}},\"Property\":\"ATK\"}}}]},\"drillFilterOtherVisuals\":true,\"hasDefaultSort\":true,\"objects\":{\"script\":[{\"properties\":{\"source\":{\"expr\":{\"Literal\":{\"Value\":\"'# The following code to create a dataframe and remove duplicated rows is always executed and acts as a preamble for your script: \\n\\n# dataset = pandas.DataFrame(Character, Element, Path, Rarity)\\n# dataset = dataset.drop_duplicates()\\n\\n# Paste or type your script code here:\\n# install.packages(\\\"GGally\\\")\\nlibrary(GGally)\\n\\nggpairs(dataset, columns = 1:4, \\n        upper = list(continuous = wrap(\\\"cor\\\", size = 4, color = ''#8B7355'')),\\n        diag = list(continuous = wrap(\\\"densityDiag\\\",color = ''#8B7355'')),\\n        lower = list(continuous = wrap(\\\"points\\\", color = ''#8B7355'')))\\n\\n'\"}}},\"provider\":{\"expr\":{\"Literal\":{\"Value\":\"'R'\"}}}}}]},\"vcObjects\":{\"title\":[{\"properties\":{\"text\":{\"expr\":{\"Literal\":{\"Value\":\"'Relationships between ATK, DEF, HP, SPD'\"}}}}}],\"subTitle\":[{\"properties\":{\"show\":{\"expr\":{\"Literal\":{\"Value\":\"true\"}}},\"text\":{\"expr\":{\"Literal\":{\"Value\":\"'From level 1, 20, 30, 40, 50, 60, 70, 80'\"}}}}}]}}}",
          "filters": "[]",
          "height": 624.00,
          "width": 608.00,
          "x": 0.00,
          "y": 96.00,
          "z": 0.00
        },
        {
          "config": "{\"name\":\"ffcb80c081bb6ec676d2\",\"layouts\":[{\"id\":0,\"position\":{\"x\":784,\"y\":96,\"z\":3000,\"width\":496,\"height\":624,\"tabOrder\":3000}}],\"singleVisual\":{\"visualType\":\"scriptVisual\",\"projections\":{\"Values\":[{\"queryRef\":\"Stats.ATK\"},{\"queryRef\":\"Stats.DEF\"},{\"queryRef\":\"Stats.HP\"},{\"queryRef\":\"Stats.Speed\"},{\"queryRef\":\"Level.Level\"}]},\"prototypeQuery\":{\"Version\":2,\"From\":[{\"Name\":\"s\",\"Entity\":\"Stats\",\"Type\":0},{\"Name\":\"l\",\"Entity\":\"Level\",\"Type\":0}],\"Select\":[{\"Column\":{\"Expression\":{\"SourceRef\":{\"Source\":\"s\"}},\"Property\":\"ATK\"},\"Name\":\"Stats.ATK\",\"NativeReferenceName\":\"ATK\"},{\"Column\":{\"Expression\":{\"SourceRef\":{\"Source\":\"s\"}},\"Property\":\"DEF\"},\"Name\":\"Stats.DEF\",\"NativeReferenceName\":\"DEF\"},{\"Column\":{\"Expression\":{\"SourceRef\":{\"Source\":\"s\"}},\"Property\":\"HP\"},\"Name\":\"Stats.HP\",\"NativeReferenceName\":\"HP\"},{\"Column\":{\"Expression\":{\"SourceRef\":{\"Source\":\"s\"}},\"Property\":\"Speed\"},\"Name\":\"Stats.Speed\",\"NativeReferenceName\":\"Speed\"},{\"Column\":{\"Expression\":{\"SourceRef\":{\"Source\":\"l\"}},\"Property\":\"Level\"},\"Name\":\"Level.Level\",\"NativeReferenceName\":\"Level\"}],\"OrderBy\":[{\"Direction\":1,\"Expression\":{\"Column\":{\"Expression\":{\"SourceRef\":{\"Source\":\"s\"}},\"Property\":\"ATK\"}}}]},\"drillFilterOtherVisuals\":true,\"hasDefaultSort\":true,\"objects\":{\"script\":[{\"properties\":{\"source\":{\"expr\":{\"Literal\":{\"Value\":\"'# The following code to create a dataframe and remove duplicated rows is always executed and acts as a preamble for your script: \\n\\n# dataset = pandas.DataFrame(Character, Element, Path, Rarity)\\n# dataset = dataset.drop_duplicates()\\n\\n# Paste or type your script code here:\\n# install.packages(\\\"GGally\\\")\\nlibrary(GGally)\\n\\nggpairs(dataset, columns = 1:4, \\n        upper = list(continuous = wrap(\\\"cor\\\", size = 4, color = ''#8B7355'')),\\n        diag = list(continuous = wrap(\\\"densityDiag\\\",color = ''#8B7355'')),\\n        lower = list(continuous = wrap(\\\"points\\\", color = ''#8B7355'')))\\n'\"}}},\"provider\":{\"expr\":{\"Literal\":{\"Value\":\"'R'\"}}}}}]},\"vcObjects\":{\"title\":[{\"properties\":{\"text\":{\"expr\":{\"Literal\":{\"Value\":\"'Relationships between ATK, DEF, HP, SPD'\"}}}}}],\"subTitle\":[{\"properties\":{\"show\":{\"expr\":{\"Literal\":{\"Value\":\"true\"}}},\"text\":{\"expr\":{\"Literal\":{\"Value\":\"'From level 80'\"}}}}}]}}}",
          "filters": "[{\"name\":\"Filter967214cac39dc3a9b142\",\"expression\":{\"Column\":{\"Expression\":{\"SourceRef\":{\"Entity\":\"Level\"}},\"Property\":\"Level\"}},\"filter\":{\"Version\":2,\"From\":[{\"Name\":\"l\",\"Entity\":\"Level\",\"Type\":0}],\"Where\":[{\"Condition\":{\"In\":{\"Expressions\":[{\"Column\":{\"Expression\":{\"SourceRef\":{\"Source\":\"l\"}},\"Property\":\"Level\"}}],\"Values\":[[{\"Literal\":{\"Value\":\"80L\"}}]]}}}]},\"type\":\"Categorical\",\"howCreated\":0,\"objects\":{},\"isHiddenInViewMode\":false}]",
          "height": 624.00,
          "width": 496.00,
          "x": 784.00,
          "y": 96.00,
          "z": 3000.00
        }
      ],
      "width": 1280.00
    },
    {
      "config": "{}",
      "displayName": "Rarity, Path, Element",
      "displayOption": 1,
      "filters": "[]",
      "height": 720.00,
      "name": "ReportSection9591133d227be0220ec9",
      "ordinal": 6,
      "visualContainers": [
        {
          "config": "{\"name\":\"46b8720d695c928acffa\",\"layouts\":[{\"id\":0,\"position\":{\"x\":16,\"y\":16,\"z\":1001,\"width\":1264.0000000000002,\"height\":704,\"tabOrder\":1001}}],\"singleVisual\":{\"visualType\":\"scriptVisual\",\"projections\":{\"Values\":[{\"queryRef\":\"Characters.Character\"},{\"queryRef\":\"Characters.Path\"},{\"queryRef\":\"Characters.Element\"},{\"queryRef\":\"Characters.Rarity\"}]},\"prototypeQuery\":{\"Version\":2,\"From\":[{\"Name\":\"c\",\"Entity\":\"Characters\",\"Type\":0}],\"Select\":[{\"Column\":{\"Expression\":{\"SourceRef\":{\"Source\":\"c\"}},\"Property\":\"Character\"},\"Name\":\"Characters.Character\",\"NativeReferenceName\":\"Character\"},{\"Column\":{\"Expression\":{\"SourceRef\":{\"Source\":\"c\"}},\"Property\":\"Path\"},\"Name\":\"Characters.Path\",\"NativeReferenceName\":\"Path\"},{\"Column\":{\"Expression\":{\"SourceRef\":{\"Source\":\"c\"}},\"Property\":\"Element\"},\"Name\":\"Characters.Element\",\"NativeReferenceName\":\"Element\"},{\"Column\":{\"Expression\":{\"SourceRef\":{\"Source\":\"c\"}},\"Property\":\"Rarity\"},\"Name\":\"Characters.Rarity\",\"NativeReferenceName\":\"Rarity\"}],\"OrderBy\":[{\"Direction\":1,\"Expression\":{\"Column\":{\"Expression\":{\"SourceRef\":{\"Source\":\"c\"}},\"Property\":\"Character\"}}}]},\"drillFilterOtherVisuals\":true,\"hasDefaultSort\":true,\"objects\":{\"script\":[{\"properties\":{\"source\":{\"expr\":{\"Literal\":{\"Value\":\"'# The following code to create a dataframe and remove duplicated rows is always executed and acts as a preamble for your script: \\n\\n# dataset <- data.frame(Character, Path, Element)\\n# dataset <- unique(dataset)\\n\\n# Paste or type your script code here:\\nlibrary(ggplot2)\\nlibrary(patchwork)\\nlibrary(treemapify)\\ndataset$Rarity <- factor(dataset$Rarity, levels = c(''5'', ''4''))\\n# Calculate the count of characters for each rarity category\\nrarity_counts <- table(dataset$Rarity)\\n\\n# Convert the result to a data frame\\nrarity_counts_df <- as.data.frame(rarity_counts)\\nnames(rarity_counts_df) <- c(\\\"Rarity\\\", \\\"count\\\")\\n\\n# Calculate the count of characters for each rarity and path combination\\nrarity_path_counts <- table(dataset$Rarity, dataset$Path, dataset$Element)\\n\\n# Convert the result to a data frame\\nrarity_path_counts_df <- as.data.frame(rarity_path_counts)\\n\\n# Rename the columns\\nnames(rarity_path_counts_df) <- c(\\\"Rarity\\\",\\\"Path\\\", \\\"Element\\\", \\\"Count\\\")\\n\\ncustom_palette <- c(\\\"Lightning\\\" = \\\"darkorchid4\\\",\\n                    \\\"Physical\\\" = \\\"lavenderblush4\\\",\\n                    \\\"Quantum\\\" = \\\"slateblue4\\\",\\n                    \\\"Wind\\\" = \\\"chartreuse2\\\",\\n                    \\\"Imaginary\\\" = \\\"gold2\\\",\\n                    \\\"Fire\\\" = \\\"brown1\\\",\\n                    \\\"Ice\\\" = \\\"cadetblue1\\\")\\n\\ncustom_xtick_colors <- c(\\\"Abundance\\\" = \\\"gold2\\\",\\n                    \\\"Destruction\\\" = \\\"brown\\\",\\n                    \\\"Erudition\\\" = \\\"red\\\",\\n                    \\\"Harmony\\\" = \\\"green\\\",\\n                    \\\"Hunt\\\" = \\\"limegreen\\\",\\n                    \\\"Nihility\\\" = \\\"purple\\\",\\n                    \\\"Preservation\\\" = \\\"cyan\\\")\\n\\ncustom_palette_r <- c(''5'' = \\\"gold\\\", ''4'' = \\\"purple\\\")\\n  \\np1 <- ggplot(rarity_path_counts_df, aes(area = Count, fill = Path, label = Element, subgroup = Rarity, subgroup2 = Path)) +\\n  geom_treemap(color = \\\"#8B8B83\\\", size = 1) +\\n  scale_fill_manual(values = custom_xtick_colors) + \\n  geom_treemap_subgroup_text(place = \\\"centre\\\", grow = TRUE,\\n                             alpha = 0.25, color = \\\"black\\\",\\n                             fontface = \\\"italic\\\") +\\n  geom_treemap_text(color = \\\"white\\\", place = \\\"centre\\\",\\n                    size = 5, grow = TRUE) +\\n  geom_treemap_subgroup_border(colour = \\\"#FFFFF0\\\", size = 5) +\\n  geom_treemap_subgroup2_border(colour = \\\"#EEEEE0\\\", size = 2) +\\n  ggtitle(\\\"Rarity, Path, and Element Distribution\\\") +\\n  theme(plot.title = element_text(size = 15, hjust = 0.5)) \\n\\np2 <- ggplot(dataset, aes(x = Rarity, fill = Rarity)) +\\n  geom_bar() +\\n  scale_fill_manual(values = custom_palette_r) +\\n  geom_text(aes(label = ..count..), stat = \\\"count\\\", vjust = -1, colour = \\\"black\\\") +\\n  labs(y = \\\"Count of Characters\\\") + ylim(c(0, 30))\\n\\np3 <- ggplot(dataset, aes(x = Path, fill = Path)) +\\n  geom_bar() +\\n  scale_fill_manual(values = custom_xtick_colors) +\\n  geom_text(aes(label = ..count..), stat = \\\"count\\\", vjust = -1, colour = \\\"black\\\") +\\n  labs(y = \\\"Count of Characters\\\") + ylim(c(0, 10))\\n\\np4 <- ggplot(dataset, aes(x = Element, fill = Element)) +\\n  geom_bar() +\\n  scale_fill_manual(values = custom_palette) +\\n  geom_text(aes(label = ..count..), stat = \\\"count\\\", vjust = -1, colour = \\\"black\\\") +\\n  labs(y = \\\"Count of Characters\\\") + ylim(c(0, 10))\\n\\np1 + (p2 / p3 / p4)'\"}}},\"provider\":{\"expr\":{\"Literal\":{\"Value\":\"'R'\"}}}}}]},\"vcObjects\":{\"title\":[{\"properties\":{\"text\":{\"expr\":{\"Literal\":{\"Value\":\"''\"}}}}}]}}}",
          "filters": "[]",
          "height": 704.00,
          "width": 1264.00,
          "x": 16.00,
          "y": 16.00,
          "z": 1001.00
        }
      ],
      "width": 1280.00
    },
    {
      "config": "{}",
      "displayName": "Stats by Rarity",
      "displayOption": 1,
      "filters": "[]",
      "height": 720.00,
      "name": "ReportSection981d2ed98d877f57c8e1",
      "ordinal": 3,
      "visualContainers": [
        {
          "config": "{\"name\":\"42c95e51ae5ed9580791\",\"layouts\":[{\"id\":0,\"position\":{\"x\":0,\"y\":48,\"z\":0,\"width\":1104,\"height\":656,\"tabOrder\":0}}],\"singleVisual\":{\"visualType\":\"scriptVisual\",\"projections\":{\"Values\":[{\"queryRef\":\"Stats.ATK\"},{\"queryRef\":\"Level.Level\"},{\"queryRef\":\"Characters.Rarity\"},{\"queryRef\":\"Stats.DEF\"},{\"queryRef\":\"Stats.HP\"},{\"queryRef\":\"Stats.Speed\"}]},\"prototypeQuery\":{\"Version\":2,\"From\":[{\"Name\":\"s\",\"Entity\":\"Stats\",\"Type\":0},{\"Name\":\"l\",\"Entity\":\"Level\",\"Type\":0},{\"Name\":\"c\",\"Entity\":\"Characters\",\"Type\":0}],\"Select\":[{\"Column\":{\"Expression\":{\"SourceRef\":{\"Source\":\"s\"}},\"Property\":\"ATK\"},\"Name\":\"Stats.ATK\",\"NativeReferenceName\":\"ATK\"},{\"Column\":{\"Expression\":{\"SourceRef\":{\"Source\":\"l\"}},\"Property\":\"Level\"},\"Name\":\"Level.Level\",\"NativeReferenceName\":\"Level\"},{\"Column\":{\"Expression\":{\"SourceRef\":{\"Source\":\"c\"}},\"Property\":\"Rarity\"},\"Name\":\"Characters.Rarity\",\"NativeReferenceName\":\"Rarity\"},{\"Column\":{\"Expression\":{\"SourceRef\":{\"Source\":\"s\"}},\"Property\":\"DEF\"},\"Name\":\"Stats.DEF\",\"NativeReferenceName\":\"DEF\"},{\"Column\":{\"Expression\":{\"SourceRef\":{\"Source\":\"s\"}},\"Property\":\"HP\"},\"Name\":\"Stats.HP\",\"NativeReferenceName\":\"HP\"},{\"Column\":{\"Expression\":{\"SourceRef\":{\"Source\":\"s\"}},\"Property\":\"Speed\"},\"Name\":\"Stats.Speed\",\"NativeReferenceName\":\"Speed\"}]},\"drillFilterOtherVisuals\":true,\"filterSortOrder\":3,\"hasDefaultSort\":true,\"objects\":{\"script\":[{\"properties\":{\"source\":{\"expr\":{\"Literal\":{\"Value\":\"'# The following code to create a dataframe and remove duplicated rows is always executed and acts as a preamble for your script: \\n\\n# dataset = pandas.DataFrame(Path, ATK)\\n# dataset = dataset.drop_duplicates()\\n\\n# Paste or type your script code here:\\n# Custom palette for different paths\\nlibrary(ggplot2)\\nlibrary(patchwork)\\n# Define custom palette\\ncustom_palette <- c(''5'' = \\\"gold\\\", ''4'' = \\\"purple\\\")\\n\\n# Convert Rarity to a factor with specified levels\\ndataset$Rarity <- factor(dataset$Rarity, levels = c(''5'', ''4''))\\n\\np1 <- ggplot(dataset, aes(x = Rarity, y = ATK, fill = Rarity)) +\\n  geom_boxplot() +\\n  scale_fill_manual(values = custom_palette) +\\n  theme(\\n    legend.position = \\\"none\\\",\\n    axis.text = element_text(size = 14),  # Adjust text size for tick labels\\n    axis.title = element_text(size = 16)  # Adjust text size for axis labels\\n  ) +\\n  labs(title = \\\"ATK at Level 80 by Rarity\\\")\\n\\np2 <- ggplot(dataset, aes(x = Rarity, y = DEF, fill = Rarity)) +\\n  geom_boxplot() +\\n  scale_fill_manual(values = custom_palette) +\\n  theme(\\n    legend.position = \\\"none\\\",\\n    axis.text = element_text(size = 14),  # Adjust text size for tick labels\\n    axis.title = element_text(size = 16)  # Adjust text size for axis labels\\n  ) +\\n  labs(title = \\\"DEF at Level 80 by Rarity\\\")\\n\\np3 <- ggplot(dataset, aes(x = Rarity, y = HP, fill = Rarity)) +\\n  geom_boxplot() +\\n  scale_fill_manual(values = custom_palette) +\\n  theme(\\n    legend.position = \\\"none\\\",\\n    axis.text = element_text(size = 14),  # Adjust text size for tick labels\\n    axis.title = element_text(size = 16)  # Adjust text size for axis labels\\n  ) +\\n  labs(title = \\\"HP at Level 80 by Rarity\\\")\\n\\np4 <- ggplot(dataset, aes(x = Rarity, y = Speed, fill = Rarity)) +\\n  geom_boxplot() +\\n  scale_fill_manual(values = custom_palette) +\\n  theme(\\n    legend.position = \\\"none\\\",\\n    axis.text = element_text(size = 14),  # Adjust text size for tick labels\\n    axis.title = element_text(size = 16)  # Adjust text size for axis labels\\n  ) +\\n  labs(title = \\\"Speed at Level 80 by Rarity\\\")\\n\\n# Combine the plots\\np1 + p2 + p3 + p4'\"}}},\"provider\":{\"expr\":{\"Literal\":{\"Value\":\"'R'\"}}}}}]},\"vcObjects\":{\"lockAspect\":[{\"properties\":{\"show\":{\"expr\":{\"Literal\":{\"Value\":\"true\"}}}}}],\"padding\":[{\"properties\":{\"left\":{\"expr\":{\"Literal\":{\"Value\":\"5D\"}}}}}],\"title\":[{\"properties\":{\"text\":{\"expr\":{\"Literal\":{\"Value\":\"'Stats at Level 80 Distribution by Rarity'\"}}},\"alignment\":{\"expr\":{\"Literal\":{\"Value\":\"'center'\"}}},\"bold\":{\"expr\":{\"Literal\":{\"Value\":\"false\"}}}}}]}}}",
          "filters": "[{\"name\":\"Filtera9f8a8b6f749bb9e13fa\",\"expression\":{\"Column\":{\"Expression\":{\"SourceRef\":{\"Entity\":\"Level\"}},\"Property\":\"Level\"}},\"filter\":{\"Version\":2,\"From\":[{\"Name\":\"l\",\"Entity\":\"Level\",\"Type\":0}],\"Where\":[{\"Condition\":{\"In\":{\"Expressions\":[{\"Column\":{\"Expression\":{\"SourceRef\":{\"Source\":\"l\"}},\"Property\":\"Level\"}}],\"Values\":[[{\"Literal\":{\"Value\":\"80L\"}}]]}}}]},\"type\":\"Categorical\",\"howCreated\":0,\"objects\":{},\"isHiddenInViewMode\":false,\"ordinal\":0},{\"name\":\"Filter5fb693bc3898eed573d7\",\"expression\":{\"Column\":{\"Expression\":{\"SourceRef\":{\"Entity\":\"Stats\"}},\"Property\":\"ATK\"}},\"type\":\"Advanced\",\"howCreated\":0,\"isHiddenInViewMode\":false,\"ordinal\":1},{\"name\":\"Filterb6bd8ec41edb43999ea4\",\"expression\":{\"Column\":{\"Expression\":{\"SourceRef\":{\"Entity\":\"Characters\"}},\"Property\":\"Rarity\"}},\"type\":\"Categorical\",\"howCreated\":0,\"objects\":{\"general\":[{\"properties\":{\"isInvertedSelectionMode\":{\"expr\":{\"Literal\":{\"Value\":\"true\"}}}}}]},\"isHiddenInViewMode\":false,\"ordinal\":2}]",
          "height": 656.00,
          "width": 1104.00,
          "x": 0.00,
          "y": 48.00,
          "z": 0.00
        },
        {
          "config": "{\"name\":\"646673d6f9754b4c3f92\",\"layouts\":[{\"id\":0,\"position\":{\"x\":480,\"y\":0,\"z\":4000,\"width\":368,\"height\":48,\"tabOrder\":4000}}],\"singleVisual\":{\"visualType\":\"textbox\",\"drillFilterOtherVisuals\":true,\"objects\":{\"general\":[{\"properties\":{\"paragraphs\":[{\"textRuns\":[{\"value\":\"Exclude Acheron, Aventurine, Gallagher\",\"textStyle\":{\"fontWeight\":\"bold\",\"fontSize\":\"14pt\"}}],\"horizontalTextAlignment\":\"center\"}]}}]}}}",
          "filters": "[]",
          "height": 48.00,
          "width": 368.00,
          "x": 480.00,
          "y": 0.00,
          "z": 4000.00
        },
        {
          "config": "{\"name\":\"721d725cf63a68072192\",\"layouts\":[{\"id\":0,\"position\":{\"x\":1104,\"y\":80,\"z\":5000,\"width\":160,\"height\":624,\"tabOrder\":5000}}],\"singleVisual\":{\"visualType\":\"textbox\",\"drillFilterOtherVisuals\":true,\"objects\":{\"general\":[{\"properties\":{\"paragraphs\":[{\"textRuns\":[{\"value\":\"5-star\",\"textStyle\":{\"fontWeight\":\"bold\",\"fontSize\":\"14pt\"}},{\"value\":\" characters tend to have higher \",\"textStyle\":{\"fontSize\":\"14pt\"}},{\"value\":\"ATK\",\"textStyle\":{\"fontWeight\":\"bold\",\"fontSize\":\"14pt\"}},{\"value\":\", \",\"textStyle\":{\"fontSize\":\"14pt\"}},{\"value\":\"DEF\",\"textStyle\":{\"fontWeight\":\"bold\",\"fontSize\":\"14pt\"}},{\"value\":\", and \",\"textStyle\":{\"fontSize\":\"14pt\"}},{\"value\":\"HP \",\"textStyle\":{\"fontWeight\":\"bold\",\"fontSize\":\"14pt\"}},{\"value\":\"than \",\"textStyle\":{\"fontSize\":\"14pt\"}},{\"value\":\"4-star\",\"textStyle\":{\"fontWeight\":\"bold\",\"fontSize\":\"14pt\"}},{\"value\":\" characters.\",\"textStyle\":{\"fontSize\":\"14pt\"}}],\"listType\":\"bullet\"},{\"textRuns\":[{\"value\":\"\"}]},{\"textRuns\":[{\"value\":\"4-star \",\"textStyle\":{\"fontWeight\":\"bold\",\"fontSize\":\"14pt\"}},{\"value\":\"characters tend to have higher \",\"textStyle\":{\"fontSize\":\"14pt\"}},{\"value\":\"Speed \",\"textStyle\":{\"fontWeight\":\"bold\",\"fontSize\":\"14pt\"}},{\"value\":\"than \",\"textStyle\":{\"fontSize\":\"14pt\"}},{\"value\":\"5-star\",\"textStyle\":{\"fontWeight\":\"bold\",\"fontSize\":\"14pt\"}},{\"value\":\" characters.\",\"textStyle\":{\"fontSize\":\"14pt\"}}],\"listType\":\"bullet\"},{\"textRuns\":[{\"value\":\"\"}]},{\"textRuns\":[{\"value\":\"\"}]}]}}]}}}",
          "filters": "[]",
          "height": 624.00,
          "width": 160.00,
          "x": 1104.00,
          "y": 80.00,
          "z": 5000.00
        }
      ],
      "width": 1280.00
    },
    {
      "config": "{}",
      "displayName": "Stat Growth % among all char",
      "displayOption": 1,
      "filters": "[]",
      "height": 720.00,
      "name": "ReportSection99663bcfdb44146c6ab3",
      "ordinal": 4,
      "visualContainers": [
        {
          "config": "{\"name\":\"36bc2b3a6d60d3058e55\",\"layouts\":[{\"id\":0,\"position\":{\"x\":352,\"y\":16,\"z\":1,\"width\":560,\"height\":48,\"tabOrder\":1}}],\"singleVisual\":{\"visualType\":\"textbox\",\"drillFilterOtherVisuals\":true,\"objects\":{\"general\":[{\"properties\":{\"paragraphs\":[{\"textRuns\":[{\"value\":\"Exclude Acheron, Aventurine, Gallagher\",\"textStyle\":{\"fontWeight\":\"bold\",\"fontSize\":\"14pt\"}}],\"horizontalTextAlignment\":\"center\"}]}}]}}}",
          "filters": "[]",
          "height": 48.00,
          "width": 560.00,
          "x": 352.00,
          "y": 16.00,
          "z": 1.00
        },
        {
          "config": "{\"name\":\"68e81779d7f2c54462b7\",\"layouts\":[{\"id\":0,\"position\":{\"x\":0,\"y\":48,\"z\":0,\"width\":1280,\"height\":672.0000000000001,\"tabOrder\":0}}],\"singleVisual\":{\"visualType\":\"scriptVisual\",\"projections\":{\"Values\":[{\"queryRef\":\"Characters.Character\"},{\"queryRef\":\"Stats.ATK Growth %\"},{\"queryRef\":\"Stats.DEF Growth %\"},{\"queryRef\":\"Stats.HP Growth %\"},{\"queryRef\":\"Stats.Speed Growth %\"},{\"queryRef\":\"Level.Level\"}]},\"prototypeQuery\":{\"Version\":2,\"From\":[{\"Name\":\"c\",\"Entity\":\"Characters\",\"Type\":0},{\"Name\":\"s\",\"Entity\":\"Stats\",\"Type\":0},{\"Name\":\"l\",\"Entity\":\"Level\",\"Type\":0}],\"Select\":[{\"Column\":{\"Expression\":{\"SourceRef\":{\"Source\":\"c\"}},\"Property\":\"Character\"},\"Name\":\"Characters.Character\",\"NativeReferenceName\":\"Character\"},{\"Column\":{\"Expression\":{\"SourceRef\":{\"Source\":\"s\"}},\"Property\":\"ATK Growth %\"},\"Name\":\"Stats.ATK Growth %\",\"NativeReferenceName\":\"ATK Growth %\"},{\"Column\":{\"Expression\":{\"SourceRef\":{\"Source\":\"s\"}},\"Property\":\"DEF Growth %\"},\"Name\":\"Stats.DEF Growth %\",\"NativeReferenceName\":\"DEF Growth %\"},{\"Column\":{\"Expression\":{\"SourceRef\":{\"Source\":\"s\"}},\"Property\":\"HP Growth %\"},\"Name\":\"Stats.HP Growth %\",\"NativeReferenceName\":\"HP Growth %\"},{\"Column\":{\"Expression\":{\"SourceRef\":{\"Source\":\"s\"}},\"Property\":\"Speed Growth %\"},\"Name\":\"Stats.Speed Growth %\",\"NativeReferenceName\":\"Speed Growth %\"},{\"Column\":{\"Expression\":{\"SourceRef\":{\"Source\":\"l\"}},\"Property\":\"Level\"},\"Name\":\"Level.Level\",\"NativeReferenceName\":\"Level\"}]},\"drillFilterOtherVisuals\":true,\"objects\":{\"script\":[{\"properties\":{\"source\":{\"expr\":{\"Literal\":{\"Value\":\"'# The following code to create a dataframe and remove duplicated rows is always executed and acts as a preamble for your script: \\n\\n# dataset <- data.frame(Character, ATK Growth %, DEF Growth %, HP Growth %, Speed Growth %)\\n# dataset <- unique(dataset)\\n\\n# Paste or type your script code here:\\nlibrary(ggplot2)\\nlibrary(patchwork)\\n\\np1 <- ggplot(dataset, aes(x = Level, y = `ATK Growth %`, color = Character)) +\\n  geom_line() + ggtitle(\\\"Stats Growth % by Level\\\") +\\n  theme(plot.title = element_text(size = 20, hjust = 2)) \\n\\np2 <- ggplot(dataset, aes(x = Level, y = `DEF Growth %`, color = Character)) +\\n  geom_line() + theme(legend.position = \\\"none\\\")\\n\\np3 <- ggplot(dataset, aes(x = Level, y = `HP Growth %`, color = Character)) +\\n  geom_line() + theme(legend.position = \\\"none\\\")\\n\\np4 <- ggplot(dataset, aes(x = Level, y = `Speed Growth %`, color = Character)) +\\n  geom_line() + theme(legend.position = \\\"none\\\")\\n\\np1 + p2 + p3 + p4'\"}}},\"provider\":{\"expr\":{\"Literal\":{\"Value\":\"'R'\"}}}}}]},\"vcObjects\":{\"title\":[{\"properties\":{\"text\":{\"expr\":{\"Literal\":{\"Value\":\"'Stats Growth % by Level'\"}}},\"show\":{\"expr\":{\"Literal\":{\"Value\":\"false\"}}}}}]}}}",
          "filters": "[]",
          "height": 672.00,
          "width": 1280.00,
          "x": 0.00,
          "y": 48.00,
          "z": 0.00
        }
      ],
      "width": 1280.00
    },
    {
      "config": "{}",
      "displayName": "Stats by Character",
      "displayOption": 1,
      "filters": "[]",
      "height": 720.00,
      "name": "ReportSectionb984f0846b195a998507",
      "ordinal": 1,
      "visualContainers": [
        {
          "config": "{\"name\":\"b5aa85f2b4ea05bb8600\",\"layouts\":[{\"id\":0,\"position\":{\"x\":640,\"y\":384,\"z\":4000,\"width\":640,\"height\":336.00000000000006,\"tabOrder\":4000}}],\"singleVisual\":{\"visualType\":\"scriptVisual\",\"projections\":{\"Values\":[{\"queryRef\":\"Level.Level\"},{\"queryRef\":\"Characters.Character\"},{\"queryRef\":\"Stats.Speed\"}]},\"prototypeQuery\":{\"Version\":2,\"From\":[{\"Name\":\"l\",\"Entity\":\"Level\",\"Type\":0},{\"Name\":\"c\",\"Entity\":\"Characters\",\"Type\":0},{\"Name\":\"s\",\"Entity\":\"Stats\",\"Type\":0}],\"Select\":[{\"Column\":{\"Expression\":{\"SourceRef\":{\"Source\":\"l\"}},\"Property\":\"Level\"},\"Name\":\"Level.Level\",\"NativeReferenceName\":\"Level\"},{\"Column\":{\"Expression\":{\"SourceRef\":{\"Source\":\"c\"}},\"Property\":\"Character\"},\"Name\":\"Characters.Character\",\"NativeReferenceName\":\"Character\"},{\"Column\":{\"Expression\":{\"SourceRef\":{\"Source\":\"s\"}},\"Property\":\"Speed\"},\"Name\":\"Stats.Speed\",\"NativeReferenceName\":\"Speed\"}],\"OrderBy\":[{\"Direction\":1,\"Expression\":{\"Column\":{\"Expression\":{\"SourceRef\":{\"Source\":\"l\"}},\"Property\":\"Level\"}}}]},\"drillFilterOtherVisuals\":true,\"filterSortOrder\":3,\"hasDefaultSort\":true,\"objects\":{\"script\":[{\"properties\":{\"source\":{\"expr\":{\"Literal\":{\"Value\":\"'# The following code to create a dataframe and remove duplicated rows is always executed and acts as a preamble for your script: \\n\\n# dataset = pandas.DataFrame(Path, ATK)\\n# dataset = dataset.drop_duplicates()\\n\\n# Paste or type your script code here:\\n# Custom palette for different paths\\n# Load the necessary library\\nlibrary(ggplot2)\\ndataset$Character <- with(dataset, reorder(Character, Speed, median))\\n# Create the boxplot using ggplot2\\nggplot(dataset, aes(x = Character, y = Speed, fill=Character)) +\\n  geom_boxplot() +\\n  theme(\\n    legend.position = \\\"none\\\",\\n    axis.text.x = element_text(angle = 90, vjust = 0.5),  # Rotate x-axis tick labels vertically\\n    axis.text = element_text(size = 12),  # Adjust text size for tick labels\\n    axis.title = element_text(size = 16)  # Adjust text size for axis labels\\n  )\\n'\"}}},\"provider\":{\"expr\":{\"Literal\":{\"Value\":\"'R'\"}}}}}]},\"vcObjects\":{\"lockAspect\":[{\"properties\":{\"show\":{\"expr\":{\"Literal\":{\"Value\":\"true\"}}}}}],\"padding\":[{\"properties\":{\"left\":{\"expr\":{\"Literal\":{\"Value\":\"0D\"}}},\"top\":{\"expr\":{\"Literal\":{\"Value\":\"0D\"}}},\"bottom\":{\"expr\":{\"Literal\":{\"Value\":\"0D\"}}},\"right\":{\"expr\":{\"Literal\":{\"Value\":\"0D\"}}}}}],\"title\":[{\"properties\":{\"text\":{\"expr\":{\"Literal\":{\"Value\":\"'Speed  by Character from Level 1, 20, 30, 40, 50, 60, 70, 80'\"}}},\"alignment\":{\"expr\":{\"Literal\":{\"Value\":\"'center'\"}}},\"bold\":{\"expr\":{\"Literal\":{\"Value\":\"false\"}}}}}],\"general\":[{\"properties\":{\"keepLayerOrder\":{\"expr\":{\"Literal\":{\"Value\":\"false\"}}}}}],\"visualHeader\":[{\"properties\":{\"show\":{\"expr\":{\"Literal\":{\"Value\":\"true\"}}}}}]}}}",
          "filters": "[{\"name\":\"Filter1f8c4c6fb9a27b74b729\",\"expression\":{\"Column\":{\"Expression\":{\"SourceRef\":{\"Entity\":\"Stats\"}},\"Property\":\"DEF\"}},\"type\":\"Advanced\",\"howCreated\":1,\"isHiddenInViewMode\":false,\"ordinal\":1},{\"name\":\"Filtercf126de4f15c8e8aaa91\",\"expression\":{\"Column\":{\"Expression\":{\"SourceRef\":{\"Entity\":\"Stats\"}},\"Property\":\"HP\"}},\"type\":\"Advanced\",\"howCreated\":1,\"isHiddenInViewMode\":false,\"ordinal\":2},{\"name\":\"Filter255dae1bb3719d7777a6\",\"expression\":{\"Column\":{\"Expression\":{\"SourceRef\":{\"Entity\":\"Characters\"}},\"Property\":\"Path\"}},\"type\":\"Categorical\",\"howCreated\":1,\"isHiddenInViewMode\":false,\"ordinal\":3},{\"name\":\"Filter85edad59c175f4369fa6\",\"expression\":{\"Column\":{\"Expression\":{\"SourceRef\":{\"Entity\":\"Stats\"}},\"Property\":\"Speed\"}},\"type\":\"Categorical\",\"howCreated\":0,\"objects\":{},\"isHiddenInViewMode\":false,\"ordinal\":4},{\"name\":\"Filter0b4d8a0ed751dc067f88\",\"expression\":{\"Column\":{\"Expression\":{\"SourceRef\":{\"Entity\":\"Level\"}},\"Property\":\"Level\"}},\"filter\":{\"Version\":2,\"From\":[{\"Name\":\"l\",\"Entity\":\"Level\",\"Type\":0}],\"Where\":[{\"Condition\":{\"In\":{\"Expressions\":[{\"Column\":{\"Expression\":{\"SourceRef\":{\"Source\":\"l\"}},\"Property\":\"Level\"}}],\"Values\":[[{\"Literal\":{\"Value\":\"80L\"}}]]}}}]},\"type\":\"Categorical\",\"howCreated\":0,\"objects\":{\"general\":[{\"properties\":{}}]},\"isHiddenInViewMode\":false}]",
          "height": 336.00,
          "width": 640.00,
          "x": 640.00,
          "y": 384.00,
          "z": 4000.00
        },
        {
          "config": "{\"name\":\"cd8787ede47300deebc0\",\"layouts\":[{\"id\":0,\"position\":{\"x\":640,\"y\":48,\"z\":2000,\"width\":640,\"height\":336.00000000000006,\"tabOrder\":2000}}],\"singleVisual\":{\"visualType\":\"scriptVisual\",\"projections\":{\"Values\":[{\"queryRef\":\"Level.Level\"},{\"queryRef\":\"Characters.Character\"},{\"queryRef\":\"Stats.DEF\"}]},\"prototypeQuery\":{\"Version\":2,\"From\":[{\"Name\":\"l\",\"Entity\":\"Level\",\"Type\":0},{\"Name\":\"c\",\"Entity\":\"Characters\",\"Type\":0},{\"Name\":\"s\",\"Entity\":\"Stats\",\"Type\":0}],\"Select\":[{\"Column\":{\"Expression\":{\"SourceRef\":{\"Source\":\"l\"}},\"Property\":\"Level\"},\"Name\":\"Level.Level\",\"NativeReferenceName\":\"Level\"},{\"Column\":{\"Expression\":{\"SourceRef\":{\"Source\":\"c\"}},\"Property\":\"Character\"},\"Name\":\"Characters.Character\",\"NativeReferenceName\":\"Character\"},{\"Column\":{\"Expression\":{\"SourceRef\":{\"Source\":\"s\"}},\"Property\":\"DEF\"},\"Name\":\"Stats.DEF\",\"NativeReferenceName\":\"DEF\"}]},\"drillFilterOtherVisuals\":true,\"filterSortOrder\":3,\"hasDefaultSort\":true,\"objects\":{\"script\":[{\"properties\":{\"source\":{\"expr\":{\"Literal\":{\"Value\":\"'# The following code to create a dataframe and remove duplicated rows is always executed and acts as a preamble for your script: \\n\\n# dataset = pandas.DataFrame(Path, ATK)\\n# dataset = dataset.drop_duplicates()\\n\\n# Paste or type your script code here:\\n# Custom palette for different paths\\n# Load the necessary library\\nlibrary(ggplot2)\\n\\ndataset$Character <- with(dataset, reorder(Character, DEF, median))\\n# Create the boxplot using ggplot2\\nggplot(dataset, aes(x = Character, y = DEF, fill = Character)) +\\n  geom_boxplot() +\\n  theme(\\n    legend.position = \\\"none\\\",\\n    axis.text.x = element_text(angle = 90, vjust = 0.5),  # Rotate x-axis tick labels vertically\\n    axis.text = element_text(size = 12),  # Adjust text size for tick labels\\n    axis.title = element_text(size = 16)  # Adjust text size for axis labels\\n  )\\n'\"}}},\"provider\":{\"expr\":{\"Literal\":{\"Value\":\"'R'\"}}}}}]},\"vcObjects\":{\"lockAspect\":[{\"properties\":{\"show\":{\"expr\":{\"Literal\":{\"Value\":\"true\"}}}}}],\"padding\":[{\"properties\":{\"left\":{\"expr\":{\"Literal\":{\"Value\":\"0D\"}}},\"top\":{\"expr\":{\"Literal\":{\"Value\":\"0D\"}}},\"bottom\":{\"expr\":{\"Literal\":{\"Value\":\"0D\"}}},\"right\":{\"expr\":{\"Literal\":{\"Value\":\"0D\"}}}}}],\"title\":[{\"properties\":{\"text\":{\"expr\":{\"Literal\":{\"Value\":\"'DEF by Character from Level 1, 20, 30, 40, 50, 60, 70, 80'\"}}},\"alignment\":{\"expr\":{\"Literal\":{\"Value\":\"'center'\"}}},\"bold\":{\"expr\":{\"Literal\":{\"Value\":\"false\"}}}}}],\"general\":[{\"properties\":{\"keepLayerOrder\":{\"expr\":{\"Literal\":{\"Value\":\"false\"}}}}}],\"visualHeader\":[{\"properties\":{\"show\":{\"expr\":{\"Literal\":{\"Value\":\"true\"}}}}}]}}}",
          "filters": "[{\"name\":\"Filter1f8c4c6fb9a27b74b729\",\"expression\":{\"Column\":{\"Expression\":{\"SourceRef\":{\"Entity\":\"Stats\"}},\"Property\":\"DEF\"}},\"type\":\"Advanced\",\"howCreated\":0,\"isHiddenInViewMode\":false,\"ordinal\":1},{\"name\":\"Filtercf126de4f15c8e8aaa91\",\"expression\":{\"Column\":{\"Expression\":{\"SourceRef\":{\"Entity\":\"Stats\"}},\"Property\":\"HP\"}},\"type\":\"Advanced\",\"howCreated\":1,\"isHiddenInViewMode\":false,\"ordinal\":2},{\"name\":\"Filter255dae1bb3719d7777a6\",\"expression\":{\"Column\":{\"Expression\":{\"SourceRef\":{\"Entity\":\"Characters\"}},\"Property\":\"Path\"}},\"type\":\"Categorical\",\"howCreated\":1,\"isHiddenInViewMode\":false,\"ordinal\":3},{\"name\":\"Filter85edad59c175f4369fa6\",\"expression\":{\"Column\":{\"Expression\":{\"SourceRef\":{\"Entity\":\"Stats\"}},\"Property\":\"Speed\"}},\"type\":\"Advanced\",\"howCreated\":1,\"isHiddenInViewMode\":false,\"ordinal\":4}]",
          "height": 336.00,
          "width": 640.00,
          "x": 640.00,
          "y": 48.00,
          "z": 2000.00
        },
        {
          "config": "{\"name\":\"cffb8a4e7a1b46ede330\",\"layouts\":[{\"id\":0,\"position\":{\"x\":480,\"y\":0,\"z\":1000,\"width\":368,\"height\":48,\"tabOrder\":1000}}],\"singleVisual\":{\"visualType\":\"textbox\",\"drillFilterOtherVisuals\":true,\"objects\":{\"general\":[{\"properties\":{\"paragraphs\":[{\"textRuns\":[{\"value\":\"Exclude Acheron, Aventurine, Gallagher\",\"textStyle\":{\"fontWeight\":\"bold\",\"fontSize\":\"14pt\"}}],\"horizontalTextAlignment\":\"center\"}]}}]}}}",
          "filters": "[]",
          "height": 48.00,
          "width": 368.00,
          "x": 480.00,
          "y": 0.00,
          "z": 1000.00
        },
        {
          "config": "{\"name\":\"e306099eb3de3b8a3645\",\"layouts\":[{\"id\":0,\"position\":{\"x\":0,\"y\":48,\"z\":0,\"width\":640,\"height\":336.00000000000006,\"tabOrder\":0}}],\"singleVisual\":{\"visualType\":\"scriptVisual\",\"projections\":{\"Values\":[{\"queryRef\":\"Stats.ATK\"},{\"queryRef\":\"Level.Level\"},{\"queryRef\":\"Characters.Character\"}]},\"prototypeQuery\":{\"Version\":2,\"From\":[{\"Name\":\"s\",\"Entity\":\"Stats\",\"Type\":0},{\"Name\":\"l\",\"Entity\":\"Level\",\"Type\":0},{\"Name\":\"c\",\"Entity\":\"Characters\",\"Type\":0}],\"Select\":[{\"Column\":{\"Expression\":{\"SourceRef\":{\"Source\":\"s\"}},\"Property\":\"ATK\"},\"Name\":\"Stats.ATK\",\"NativeReferenceName\":\"ATK\"},{\"Column\":{\"Expression\":{\"SourceRef\":{\"Source\":\"l\"}},\"Property\":\"Level\"},\"Name\":\"Level.Level\",\"NativeReferenceName\":\"Level\"},{\"Column\":{\"Expression\":{\"SourceRef\":{\"Source\":\"c\"}},\"Property\":\"Character\"},\"Name\":\"Characters.Character\",\"NativeReferenceName\":\"Character\"}]},\"drillFilterOtherVisuals\":true,\"filterSortOrder\":3,\"hasDefaultSort\":true,\"objects\":{\"script\":[{\"properties\":{\"source\":{\"expr\":{\"Literal\":{\"Value\":\"'# The following code to create a dataframe and remove duplicated rows is always executed and acts as a preamble for your script: \\n\\n# dataset = pandas.DataFrame(Path, ATK)\\n# dataset = dataset.drop_duplicates()\\n\\n# Paste or type your script code here:\\n# Custom palette for different paths\\n# Load the necessary library\\nlibrary(ggplot2)\\n\\ndataset$Character <- with(dataset, reorder(Character, ATK, median))\\n# Create the boxplot using ggplot2\\nggplot(dataset, aes(x = Character, y = ATK, fill = Character)) +\\n  geom_boxplot() +\\n  theme(\\n    legend.position = \\\"none\\\",\\n    axis.text.x = element_text(angle = 90, vjust = 0.5),  # Rotate x-axis tick labels vertically\\n    axis.text = element_text(size = 12),  # Adjust text size for tick labels\\n    axis.title = element_text(size = 16)  # Adjust text size for axis labels\\n  )\\n'\"}}},\"provider\":{\"expr\":{\"Literal\":{\"Value\":\"'R'\"}}}}}]},\"vcObjects\":{\"lockAspect\":[{\"properties\":{\"show\":{\"expr\":{\"Literal\":{\"Value\":\"true\"}}}}}],\"padding\":[{\"properties\":{\"left\":{\"expr\":{\"Literal\":{\"Value\":\"0D\"}}},\"top\":{\"expr\":{\"Literal\":{\"Value\":\"0D\"}}},\"bottom\":{\"expr\":{\"Literal\":{\"Value\":\"0D\"}}},\"right\":{\"expr\":{\"Literal\":{\"Value\":\"0D\"}}}}}],\"title\":[{\"properties\":{\"text\":{\"expr\":{\"Literal\":{\"Value\":\"'ATK  by Character from Level 1, 20, 30, 40, 50, 60, 70, 80'\"}}},\"alignment\":{\"expr\":{\"Literal\":{\"Value\":\"'center'\"}}},\"bold\":{\"expr\":{\"Literal\":{\"Value\":\"false\"}}}}}],\"general\":[{\"properties\":{\"keepLayerOrder\":{\"expr\":{\"Literal\":{\"Value\":\"false\"}}}}}],\"visualHeader\":[{\"properties\":{\"show\":{\"expr\":{\"Literal\":{\"Value\":\"true\"}}}}}]}}}",
          "filters": "[{\"name\":\"Filter1f8c4c6fb9a27b74b729\",\"expression\":{\"Column\":{\"Expression\":{\"SourceRef\":{\"Entity\":\"Stats\"}},\"Property\":\"DEF\"}},\"type\":\"Advanced\",\"howCreated\":1,\"isHiddenInViewMode\":false,\"ordinal\":1},{\"name\":\"Filtercf126de4f15c8e8aaa91\",\"expression\":{\"Column\":{\"Expression\":{\"SourceRef\":{\"Entity\":\"Stats\"}},\"Property\":\"HP\"}},\"type\":\"Advanced\",\"howCreated\":1,\"isHiddenInViewMode\":false,\"ordinal\":2},{\"name\":\"Filter255dae1bb3719d7777a6\",\"expression\":{\"Column\":{\"Expression\":{\"SourceRef\":{\"Entity\":\"Characters\"}},\"Property\":\"Path\"}},\"type\":\"Categorical\",\"howCreated\":1,\"isHiddenInViewMode\":false,\"ordinal\":3},{\"name\":\"Filter85edad59c175f4369fa6\",\"expression\":{\"Column\":{\"Expression\":{\"SourceRef\":{\"Entity\":\"Stats\"}},\"Property\":\"Speed\"}},\"type\":\"Advanced\",\"howCreated\":1,\"isHiddenInViewMode\":false,\"ordinal\":4}]",
          "height": 336.00,
          "width": 640.00,
          "x": 0.00,
          "y": 48.00,
          "z": 0.00
        },
        {
          "config": "{\"name\":\"eb730440ca97523734a6\",\"layouts\":[{\"id\":0,\"position\":{\"x\":0,\"y\":384,\"z\":3000,\"width\":640,\"height\":336.00000000000006,\"tabOrder\":3000}}],\"singleVisual\":{\"visualType\":\"scriptVisual\",\"projections\":{\"Values\":[{\"queryRef\":\"Level.Level\"},{\"queryRef\":\"Characters.Character\"},{\"queryRef\":\"Stats.HP\"}]},\"prototypeQuery\":{\"Version\":2,\"From\":[{\"Name\":\"l\",\"Entity\":\"Level\",\"Type\":0},{\"Name\":\"c\",\"Entity\":\"Characters\",\"Type\":0},{\"Name\":\"s\",\"Entity\":\"Stats\",\"Type\":0}],\"Select\":[{\"Column\":{\"Expression\":{\"SourceRef\":{\"Source\":\"l\"}},\"Property\":\"Level\"},\"Name\":\"Level.Level\",\"NativeReferenceName\":\"Level\"},{\"Column\":{\"Expression\":{\"SourceRef\":{\"Source\":\"c\"}},\"Property\":\"Character\"},\"Name\":\"Characters.Character\",\"NativeReferenceName\":\"Character\"},{\"Column\":{\"Expression\":{\"SourceRef\":{\"Source\":\"s\"}},\"Property\":\"HP\"},\"Name\":\"Stats.HP\",\"NativeReferenceName\":\"HP\"}]},\"drillFilterOtherVisuals\":true,\"filterSortOrder\":3,\"hasDefaultSort\":true,\"objects\":{\"script\":[{\"properties\":{\"source\":{\"expr\":{\"Literal\":{\"Value\":\"'# The following code to create a dataframe and remove duplicated rows is always executed and acts as a preamble for your script: \\n\\n# dataset = pandas.DataFrame(Path, ATK)\\n# dataset = dataset.drop_duplicates()\\n\\n# Paste or type your script code here:\\n# Custom palette for different paths\\n# Load the necessary library\\nlibrary(ggplot2)\\n\\ndataset$Character <- with(dataset, reorder(Character, HP, median))\\n# Create the boxplot using ggplot2\\nggplot(dataset, aes(x = Character, y = HP, fill = Character)) +\\n  geom_boxplot() +\\n  theme(\\n    legend.position = \\\"none\\\",\\n    axis.text.x = element_text(angle = 90, vjust = 0.5),  # Rotate x-axis tick labels vertically\\n    axis.text = element_text(size = 12),  # Adjust text size for tick labels\\n    axis.title = element_text(size = 16)  # Adjust text size for axis labels\\n  )\\n'\"}}},\"provider\":{\"expr\":{\"Literal\":{\"Value\":\"'R'\"}}}}}]},\"vcObjects\":{\"lockAspect\":[{\"properties\":{\"show\":{\"expr\":{\"Literal\":{\"Value\":\"true\"}}}}}],\"padding\":[{\"properties\":{\"left\":{\"expr\":{\"Literal\":{\"Value\":\"0D\"}}},\"top\":{\"expr\":{\"Literal\":{\"Value\":\"0D\"}}},\"bottom\":{\"expr\":{\"Literal\":{\"Value\":\"0D\"}}},\"right\":{\"expr\":{\"Literal\":{\"Value\":\"0D\"}}}}}],\"title\":[{\"properties\":{\"text\":{\"expr\":{\"Literal\":{\"Value\":\"'HP by Character from Level 1, 20, 30, 40, 50, 60, 70, 80'\"}}},\"alignment\":{\"expr\":{\"Literal\":{\"Value\":\"'center'\"}}},\"bold\":{\"expr\":{\"Literal\":{\"Value\":\"false\"}}}}}],\"general\":[{\"properties\":{\"keepLayerOrder\":{\"expr\":{\"Literal\":{\"Value\":\"false\"}}}}}],\"visualHeader\":[{\"properties\":{\"show\":{\"expr\":{\"Literal\":{\"Value\":\"true\"}}}}}]}}}",
          "filters": "[{\"name\":\"Filter1f8c4c6fb9a27b74b729\",\"expression\":{\"Column\":{\"Expression\":{\"SourceRef\":{\"Entity\":\"Stats\"}},\"Property\":\"DEF\"}},\"type\":\"Advanced\",\"howCreated\":1,\"isHiddenInViewMode\":false,\"ordinal\":1},{\"name\":\"Filtercf126de4f15c8e8aaa91\",\"expression\":{\"Column\":{\"Expression\":{\"SourceRef\":{\"Entity\":\"Stats\"}},\"Property\":\"HP\"}},\"type\":\"Advanced\",\"howCreated\":0,\"isHiddenInViewMode\":false,\"ordinal\":2},{\"name\":\"Filter255dae1bb3719d7777a6\",\"expression\":{\"Column\":{\"Expression\":{\"SourceRef\":{\"Entity\":\"Characters\"}},\"Property\":\"Path\"}},\"type\":\"Categorical\",\"howCreated\":1,\"isHiddenInViewMode\":false,\"ordinal\":3},{\"name\":\"Filter85edad59c175f4369fa6\",\"expression\":{\"Column\":{\"Expression\":{\"SourceRef\":{\"Entity\":\"Stats\"}},\"Property\":\"Speed\"}},\"type\":\"Advanced\",\"howCreated\":1,\"isHiddenInViewMode\":false,\"ordinal\":4}]",
          "height": 336.00,
          "width": 640.00,
          "x": 0.00,
          "y": 384.00,
          "z": 3000.00
        }
      ],
      "width": 1280.00
    },
    {
      "config": "{}",
      "displayName": "Stat Growth among all char",
      "displayOption": 1,
      "filters": "[]",
      "height": 720.00,
      "name": "ReportSectionca525766090006367908",
      "ordinal": 5,
      "visualContainers": [
        {
          "config": "{\"name\":\"5e2d91210ba389beb070\",\"layouts\":[{\"id\":0,\"position\":{\"x\":24,\"y\":72,\"z\":0,\"width\":1248,\"height\":648,\"tabOrder\":0}}],\"singleVisual\":{\"visualType\":\"scriptVisual\",\"projections\":{\"Values\":[{\"queryRef\":\"Level.Level\"},{\"queryRef\":\"Characters.Character\"},{\"queryRef\":\"Stats.DEF Growth\"},{\"queryRef\":\"Stats.HP Growth\"},{\"queryRef\":\"Stats.Speed Growth\"},{\"queryRef\":\"Stats.ATK Growth\"}]},\"prototypeQuery\":{\"Version\":2,\"From\":[{\"Name\":\"l\",\"Entity\":\"Level\",\"Type\":0},{\"Name\":\"h\",\"Entity\":\"Stats\",\"Type\":0},{\"Name\":\"c\",\"Entity\":\"Characters\",\"Type\":0}],\"Select\":[{\"Column\":{\"Expression\":{\"SourceRef\":{\"Source\":\"l\"}},\"Property\":\"Level\"},\"Name\":\"Level.Level\",\"NativeReferenceName\":\"Level\"},{\"Column\":{\"Expression\":{\"SourceRef\":{\"Source\":\"c\"}},\"Property\":\"Character\"},\"Name\":\"Characters.Character\",\"NativeReferenceName\":\"Character\"},{\"Column\":{\"Expression\":{\"SourceRef\":{\"Source\":\"h\"}},\"Property\":\"DEF Growth\"},\"Name\":\"Stats.DEF Growth\",\"NativeReferenceName\":\"DEF Growth\"},{\"Column\":{\"Expression\":{\"SourceRef\":{\"Source\":\"h\"}},\"Property\":\"HP Growth\"},\"Name\":\"Stats.HP Growth\",\"NativeReferenceName\":\"HP Growth\"},{\"Column\":{\"Expression\":{\"SourceRef\":{\"Source\":\"h\"}},\"Property\":\"Speed Growth\"},\"Name\":\"Stats.Speed Growth\",\"NativeReferenceName\":\"Speed Growth\"},{\"Column\":{\"Expression\":{\"SourceRef\":{\"Source\":\"h\"}},\"Property\":\"ATK Growth\"},\"Name\":\"Stats.ATK Growth\",\"NativeReferenceName\":\"ATK Growth\"}],\"OrderBy\":[{\"Direction\":1,\"Expression\":{\"Column\":{\"Expression\":{\"SourceRef\":{\"Source\":\"l\"}},\"Property\":\"Level\"}}}]},\"columnProperties\":{\"Sum(hsr_updated.ATK Growth %)\":{\"displayName\":\"ATK Growth %\"},\"hsr_updated.Source.Name\":{\"displayName\":\"Characters\"},\"Sum(hsr_updated.ATK Growth)\":{\"displayName\":\"ATK Growth\"},\"Sum(hsr_updated (2).ATK Growth)\":{\"displayName\":\"ATK Growth\"}},\"drillFilterOtherVisuals\":true,\"objects\":{\"script\":[{\"properties\":{\"source\":{\"expr\":{\"Literal\":{\"Value\":\"'# The following code to create a dataframe and remove duplicated rows is always executed and acts as a preamble for your script: \\n\\n# dataset <- data.frame(Level, ATK Growth, Character)\\n# dataset <- unique(dataset)\\n\\n# Paste or type your script code here:\\nlibrary(ggplot2)\\nlibrary(patchwork)\\n\\np1 <- ggplot(dataset, aes(x = Level, y = `ATK Growth`, color = Character)) +\\n        geom_line() + ggtitle(\\\"Stats Growth by Level\\\") +\\n  theme(plot.title = element_text(size = 15, hjust = 0.5)) \\n\\np2 <- ggplot(dataset, aes(x = Level, y = `DEF Growth`, color = Character)) +\\n  geom_line() + theme(legend.position = \\\"none\\\")\\n\\np3 <- ggplot(dataset, aes(x = Level, y = `HP Growth`, color = Character)) +\\n  geom_line() + theme(legend.position = \\\"none\\\")\\n\\np4 <- ggplot(dataset, aes(x = Level, y = `Speed Growth`, color = Character)) +\\n  geom_line() + theme(legend.position = \\\"none\\\")\\n\\np1 + p2 + p3 + p4'\"}}},\"provider\":{\"expr\":{\"Literal\":{\"Value\":\"'R'\"}}}}}]},\"vcObjects\":{\"title\":[{\"properties\":{\"show\":{\"expr\":{\"Literal\":{\"Value\":\"false\"}}}}}]}}}",
          "filters": "[]",
          "height": 648.00,
          "width": 1248.00,
          "x": 24.00,
          "y": 72.00,
          "z": 0.00
        },
        {
          "config": "{\"name\":\"c33bb67203cb8658d67c\",\"layouts\":[{\"id\":0,\"position\":{\"x\":352,\"y\":16,\"z\":4000,\"width\":560,\"height\":48,\"tabOrder\":4000}}],\"singleVisual\":{\"visualType\":\"textbox\",\"drillFilterOtherVisuals\":true,\"objects\":{\"general\":[{\"properties\":{\"paragraphs\":[{\"textRuns\":[{\"value\":\"Exclude Acheron, Aventurine, Gallagher\",\"textStyle\":{\"fontWeight\":\"bold\",\"fontSize\":\"14pt\"}}],\"horizontalTextAlignment\":\"center\"}]}}]}}}",
          "filters": "[]",
          "height": 48.00,
          "width": 560.00,
          "x": 352.00,
          "y": 16.00,
          "z": 4000.00
        }
      ],
      "width": 1280.00
    },
    {
      "config": "{}",
      "displayName": "Stats by Path",
      "displayOption": 1,
      "filters": "[]",
      "height": 720.00,
      "name": "ReportSectiond11c974a68af1bae680f",
      "ordinal": 2,
      "visualContainers": [
        {
          "config": "{\"name\":\"093bd47dc94142700f60\",\"layouts\":[{\"id\":0,\"position\":{\"x\":0,\"y\":48,\"z\":0,\"width\":1120,\"height\":640,\"tabOrder\":0}}],\"singleVisual\":{\"visualType\":\"scriptVisual\",\"projections\":{\"Values\":[{\"queryRef\":\"Characters.Path\"},{\"queryRef\":\"Stats.ATK\"},{\"queryRef\":\"Level.Level\"},{\"queryRef\":\"Stats.DEF\"},{\"queryRef\":\"Stats.HP\"},{\"queryRef\":\"Stats.Speed\"}]},\"prototypeQuery\":{\"Version\":2,\"From\":[{\"Name\":\"c\",\"Entity\":\"Characters\",\"Type\":0},{\"Name\":\"s\",\"Entity\":\"Stats\",\"Type\":0},{\"Name\":\"l\",\"Entity\":\"Level\",\"Type\":0}],\"Select\":[{\"Column\":{\"Expression\":{\"SourceRef\":{\"Source\":\"c\"}},\"Property\":\"Path\"},\"Name\":\"Characters.Path\",\"NativeReferenceName\":\"Path\"},{\"Column\":{\"Expression\":{\"SourceRef\":{\"Source\":\"s\"}},\"Property\":\"ATK\"},\"Name\":\"Stats.ATK\",\"NativeReferenceName\":\"ATK\"},{\"Column\":{\"Expression\":{\"SourceRef\":{\"Source\":\"l\"}},\"Property\":\"Level\"},\"Name\":\"Level.Level\",\"NativeReferenceName\":\"Level\"},{\"Column\":{\"Expression\":{\"SourceRef\":{\"Source\":\"s\"}},\"Property\":\"DEF\"},\"Name\":\"Stats.DEF\",\"NativeReferenceName\":\"DEF\"},{\"Column\":{\"Expression\":{\"SourceRef\":{\"Source\":\"s\"}},\"Property\":\"HP\"},\"Name\":\"Stats.HP\",\"NativeReferenceName\":\"HP\"},{\"Column\":{\"Expression\":{\"SourceRef\":{\"Source\":\"s\"}},\"Property\":\"Speed\"},\"Name\":\"Stats.Speed\",\"NativeReferenceName\":\"Speed\"}],\"OrderBy\":[{\"Direction\":1,\"Expression\":{\"Column\":{\"Expression\":{\"SourceRef\":{\"Source\":\"c\"}},\"Property\":\"Path\"}}}]},\"drillFilterOtherVisuals\":true,\"filterSortOrder\":3,\"hasDefaultSort\":true,\"objects\":{\"script\":[{\"properties\":{\"source\":{\"expr\":{\"Literal\":{\"Value\":\"'# The following code to create a dataframe and remove duplicated rows is always executed and acts as a preamble for your script: \\n\\n# dataset = pandas.DataFrame(Path, ATK)\\n# dataset = dataset.drop_duplicates()\\n\\n# Paste or type your script code here:\\n# Custom palette for different paths\\nlibrary(ggplot2)\\nlibrary(patchwork)\\n\\ncustom_palette <- c(\\\"Abundance\\\" = \\\"gold\\\",\\n                    \\\"Destruction\\\" = \\\"brown\\\",\\n                    \\\"Hunt\\\" = \\\"limegreen\\\",\\n                    \\\"Harmony\\\" = \\\"green\\\",\\n                    \\\"Erudition\\\" = \\\"red\\\",\\n                    \\\"Preservation\\\" = \\\"cyan\\\",\\n                    \\\"Nihility\\\" = \\\"purple\\\")\\n                    \\np1 <- ggplot(dataset, aes(x = Path, y = ATK, fill = Path)) +\\n  geom_boxplot() +\\n  scale_fill_manual(values=custom_palette) +\\n  theme(\\n    legend.position = \\\"none\\\",\\n    axis.text.x = element_text(angle = 90, vjust = 0.5),  # Rotate x-axis tick labels vertically\\n    axis.text = element_text(size = 12),  # Adjust text size for tick labels\\n    axis.title = element_text(size = 16)  # Adjust text size for axis labels\\n  ) + labs(title = \\\"ATK at Level 80 by Path\\\")\\n\\np2 <- ggplot(dataset, aes(x = Path, y = DEF, fill = Path)) +\\n  geom_boxplot() +\\n  scale_fill_manual(values=custom_palette) +\\n  theme(\\n    legend.position = \\\"none\\\",\\n    axis.text.x = element_text(angle = 90, vjust = 0.5),  # Rotate x-axis tick labels vertically\\n    axis.text = element_text(size = 12),  # Adjust text size for tick labels\\n    axis.title = element_text(size = 16)  # Adjust text size for axis labels\\n  ) + labs(title = \\\"DEF at Level 80 by Path\\\")\\n\\np3 <- ggplot(dataset, aes(x = Path, y = HP, fill = Path)) +\\n  geom_boxplot() +\\n  scale_fill_manual(values=custom_palette) +\\n  theme(\\n    legend.position = \\\"none\\\",\\n    axis.text.x = element_text(angle = 90, vjust = 0.5),  # Rotate x-axis tick labels vertically\\n    axis.text = element_text(size = 12),  # Adjust text size for tick labels\\n    axis.title = element_text(size = 16)  # Adjust text size for axis labels\\n  ) + labs(title = \\\"HP at Level 80 by Path\\\")\\n\\np4 <- ggplot(dataset, aes(x = Path, y = Speed, fill = Path)) +\\n  geom_boxplot() +\\n  scale_fill_manual(values=custom_palette) +\\n  theme(\\n    legend.position = \\\"none\\\",\\n    axis.text.x = element_text(angle = 90, vjust = 0.5),  # Rotate x-axis tick labels vertically\\n    axis.text = element_text(size = 12),  # Adjust text size for tick labels\\n    axis.title = element_text(size = 16)  # Adjust text size for axis labels\\n  ) + labs(title = \\\"Speed at Level 80 by Path\\\")\\n\\np1 + p2 + p3 + p4'\"}}},\"provider\":{\"expr\":{\"Literal\":{\"Value\":\"'R'\"}}}}}]},\"vcObjects\":{\"lockAspect\":[{\"properties\":{\"show\":{\"expr\":{\"Literal\":{\"Value\":\"true\"}}}}}],\"padding\":[{\"properties\":{\"left\":{\"expr\":{\"Literal\":{\"Value\":\"5D\"}}}}}],\"title\":[{\"properties\":{\"text\":{\"expr\":{\"Literal\":{\"Value\":\"'Stats at Level 80 Distribution by Path'\"}}},\"alignment\":{\"expr\":{\"Literal\":{\"Value\":\"'center'\"}}},\"bold\":{\"expr\":{\"Literal\":{\"Value\":\"false\"}}}}}]}}}",
          "filters": "[{\"name\":\"Filter1f8c4c6fb9a27b74b729\",\"expression\":{\"Column\":{\"Expression\":{\"SourceRef\":{\"Entity\":\"Stats\"}},\"Property\":\"DEF\"}},\"type\":\"Advanced\",\"howCreated\":0,\"isHiddenInViewMode\":false,\"ordinal\":1},{\"name\":\"Filtercf126de4f15c8e8aaa91\",\"expression\":{\"Column\":{\"Expression\":{\"SourceRef\":{\"Entity\":\"Stats\"}},\"Property\":\"HP\"}},\"type\":\"Advanced\",\"howCreated\":0,\"isHiddenInViewMode\":false,\"ordinal\":2},{\"name\":\"Filter85edad59c175f4369fa6\",\"expression\":{\"Column\":{\"Expression\":{\"SourceRef\":{\"Entity\":\"Stats\"}},\"Property\":\"Speed\"}},\"type\":\"Advanced\",\"howCreated\":0,\"isHiddenInViewMode\":false,\"ordinal\":4},{\"name\":\"Filtera9f8a8b6f749bb9e13fa\",\"expression\":{\"Column\":{\"Expression\":{\"SourceRef\":{\"Entity\":\"Level\"}},\"Property\":\"Level\"}},\"filter\":{\"Version\":2,\"From\":[{\"Name\":\"l\",\"Entity\":\"Level\",\"Type\":0}],\"Where\":[{\"Condition\":{\"In\":{\"Expressions\":[{\"Column\":{\"Expression\":{\"SourceRef\":{\"Source\":\"l\"}},\"Property\":\"Level\"}}],\"Values\":[[{\"Literal\":{\"Value\":\"80L\"}}]]}}}]},\"type\":\"Categorical\",\"howCreated\":0,\"objects\":{},\"isHiddenInViewMode\":false}]",
          "height": 640.00,
          "width": 1120.00,
          "x": 0.00,
          "y": 48.00,
          "z": 0.00
        },
        {
          "config": "{\"name\":\"bbf0564c906bf9687833\",\"layouts\":[{\"id\":0,\"position\":{\"x\":480,\"y\":0,\"z\":4000,\"width\":368,\"height\":48,\"tabOrder\":4000}}],\"singleVisual\":{\"visualType\":\"textbox\",\"drillFilterOtherVisuals\":true,\"objects\":{\"general\":[{\"properties\":{\"paragraphs\":[{\"textRuns\":[{\"value\":\"Exclude Acheron, Aventurine, Gallagher\",\"textStyle\":{\"fontWeight\":\"bold\",\"fontSize\":\"14pt\"}}],\"horizontalTextAlignment\":\"center\"}]}}]}}}",
          "filters": "[]",
          "height": 48.00,
          "width": 368.00,
          "x": 480.00,
          "y": 0.00,
          "z": 4000.00
        },
        {
          "config": "{\"name\":\"c5eac799752a7c80aef0\",\"layouts\":[{\"id\":0,\"position\":{\"x\":1120,\"y\":48,\"z\":5000,\"width\":160,\"height\":624,\"tabOrder\":5000}}],\"singleVisual\":{\"visualType\":\"textbox\",\"drillFilterOtherVisuals\":true,\"objects\":{\"general\":[{\"properties\":{\"paragraphs\":[{\"textRuns\":[{\"value\":\"Erudition \",\"textStyle\":{\"fontWeight\":\"bold\",\"fontSize\":\"14pt\"}},{\"value\":\"characters tend to have the highest \",\"textStyle\":{\"fontSize\":\"14pt\"}},{\"value\":\"ATK\",\"textStyle\":{\"fontWeight\":\"bold\",\"fontSize\":\"14pt\"}},{\"value\":\".\",\"textStyle\":{\"fontSize\":\"14pt\"}}],\"listType\":\"bullet\"},{\"textRuns\":[{\"value\":\"\"}]},{\"textRuns\":[{\"value\":\"Preservation \",\"textStyle\":{\"fontWeight\":\"bold\",\"fontSize\":\"14pt\"}},{\"value\":\"characters tend to have the highest \",\"textStyle\":{\"fontSize\":\"14pt\"}},{\"value\":\"DEF \",\"textStyle\":{\"fontWeight\":\"bold\",\"fontSize\":\"14pt\"}},{\"value\":\"and \",\"textStyle\":{\"fontSize\":\"14pt\"}},{\"value\":\"HP\",\"textStyle\":{\"fontWeight\":\"bold\",\"fontSize\":\"14pt\"}},{\"value\":\".\",\"textStyle\":{\"fontSize\":\"14pt\"}}],\"listType\":\"bullet\"},{\"textRuns\":[{\"value\":\"\"}]},{\"textRuns\":[{\"value\":\"Hunt \",\"textStyle\":{\"fontWeight\":\"bold\",\"fontSize\":\"14pt\"}},{\"value\":\"characters tend to have the highest \",\"textStyle\":{\"fontSize\":\"14pt\"}},{\"value\":\"Speed\",\"textStyle\":{\"fontWeight\":\"bold\",\"fontSize\":\"14pt\"}},{\"value\":\".\",\"textStyle\":{\"fontSize\":\"14pt\"}}],\"listType\":\"bullet\"},{\"textRuns\":[{\"value\":\"\"}]},{\"textRuns\":[{\"value\":\"\"}]}]}}]}}}",
          "filters": "[]",
          "height": 624.00,
          "width": 160.00,
          "x": 1120.00,
          "y": 48.00,
          "z": 5000.00
        }
      ],
      "width": 1280.00
    }
  ]
}